{
    "/js/app.js": "/js/app.js",
    "/css/app.css": "/css/app.css",
    "/js/app.4311de81fd72e06ba332.hot-update.js": "/js/app.4311de81fd72e06ba332.hot-update.js",
    "/js/app.b1cc5a474234581e5b25.hot-update.js": "/js/app.b1cc5a474234581e5b25.hot-update.js",
    "/js/app.4c18ed5119755a57156a.hot-update.js": "/js/app.4c18ed5119755a57156a.hot-update.js",
    "/js/app.1dafffc9842c07f54f64.hot-update.js": "/js/app.1dafffc9842c07f54f64.hot-update.js",
    "/js/app.86e75502c91e161f8eeb.hot-update.js": "/js/app.86e75502c91e161f8eeb.hot-update.js",
    "/js/app.6f805cc43d3d4a24c84a.hot-update.js": "/js/app.6f805cc43d3d4a24c84a.hot-update.js",
    "/js/app.f36b381d2d8974442e31.hot-update.js": "/js/app.f36b381d2d8974442e31.hot-update.js",
    "/js/app.9272049b943c37c2199a.hot-update.js": "/js/app.9272049b943c37c2199a.hot-update.js",
    "/js/app.b9bbabf77f7e5d512fb8.hot-update.js": "/js/app.b9bbabf77f7e5d512fb8.hot-update.js",
    "/js/app.fead32d2246a9aa502de.hot-update.js": "/js/app.fead32d2246a9aa502de.hot-update.js",
    "/js/app.046d2a28c62618a00279.hot-update.js": "/js/app.046d2a28c62618a00279.hot-update.js",
    "/js/app.3c23c99382df33473520.hot-update.js": "/js/app.3c23c99382df33473520.hot-update.js",
    "/js/app.cbddad62afb3857b6518.hot-update.js": "/js/app.cbddad62afb3857b6518.hot-update.js",
    "/js/app.7bbf01a81d81c5946742.hot-update.js": "/js/app.7bbf01a81d81c5946742.hot-update.js",
    "/js/app.b095ed740d7cbc86c086.hot-update.js": "/js/app.b095ed740d7cbc86c086.hot-update.js",
    "/js/app.ff7b79c56261ed268cc7.hot-update.js": "/js/app.ff7b79c56261ed268cc7.hot-update.js",
    "/js/app.39979c6378c8edcc6818.hot-update.js": "/js/app.39979c6378c8edcc6818.hot-update.js"
}
